README.md
setup.py
pyjbox/__init__.py
pyjbox/command_line.py
pyjbox/downloader.py
pyjbox/jbox.py
pyjbox/terminal_size.py
pyjbox.egg-info/PKG-INFO
pyjbox.egg-info/SOURCES.txt
pyjbox.egg-info/dependency_links.txt
pyjbox.egg-info/entry_points.txt
pyjbox.egg-info/not-zip-safe
pyjbox.egg-info/requires.txt
pyjbox.egg-info/top_level.txt