Metadata-Version: 1.0
Name: pyjbox
Version: 1.3
Summary: jBox downloader with multiple threads and resume from break point support!
Home-page: http://github.com/hebingchang/pyjbox
Author: hebingchang
Author-email: hebingchang@sjtu.edu.cn
License: MIT
Platform: UNKNOWN
